py_singleline/__init__.py
py_singleline/__main__.py
py_singleline/args.py
py_singleline/builder.py
py_singleline/parser.py
py_singleline/py_singleline.py
py_singleline/spawn.py
py_singleline/tokeniser.py
py_singleline/modes/bare.py
py_singleline/modes/csv.py
py_singleline/modes/json.py
py_singleline/modes/lines.py
pysln/__main__.py
pysln/pysln.py
py_singleline-1.0.0a2.dist-info/LICENSE
py_singleline-1.0.0a2.dist-info/METADATA
py_singleline-1.0.0a2.dist-info/WHEEL
py_singleline-1.0.0a2.dist-info/entry_points.txt
py_singleline-1.0.0a2.dist-info/top_level.txt
py_singleline-1.0.0a2.dist-info/RECORD
