Metadata-Version: 2.1
Name: py-singleline
Version: 1.0.0a2
Summary: Arbitrarily complex single-line Python scripts
Home-page: http://github.com/whisperity/py-singleline
Author: Whisperity
Author-email: whisperity-packages@protonmail.com
License: GPLv3+
Keywords: python shell pipeline script scripting
Classifier: Development Status :: 3 - Alpha
Classifier: Environment :: Console
Classifier: Intended Audience :: End Users/Desktop
Classifier: Intended Audience :: Information Technology
Classifier: Intended Audience :: System Administrators
Classifier: License :: OSI Approved :: GNU General Public License v3 or later (GPLv3+)
Classifier: Operating System :: MacOS
Classifier: Operating System :: POSIX :: Linux
Classifier: Operating System :: Unix
Classifier: Programming Language :: Python :: 3 :: Only
Classifier: Topic :: Software Development
Classifier: Topic :: System :: Shells
Requires-Python: >=3.6
License-File: LICENSE
